fast_tsne/__init__.py
fast_tsne-0.0.0.0.1.dist-info/METADATA
fast_tsne-0.0.0.0.1.dist-info/WHEEL
fast_tsne-0.0.0.0.1.dist-info/top_level.txt
fast_tsne-0.0.0.0.1.dist-info/RECORD
